mypy_boto3_iot1click_projects/__init__.py
mypy_boto3_iot1click_projects/__init__.pyi
mypy_boto3_iot1click_projects/__main__.py
mypy_boto3_iot1click_projects/client.py
mypy_boto3_iot1click_projects/client.pyi
mypy_boto3_iot1click_projects/literals.py
mypy_boto3_iot1click_projects/literals.pyi
mypy_boto3_iot1click_projects/paginator.py
mypy_boto3_iot1click_projects/paginator.pyi
mypy_boto3_iot1click_projects/py.typed
mypy_boto3_iot1click_projects/type_defs.py
mypy_boto3_iot1click_projects/type_defs.pyi
mypy_boto3_iot1click_projects/version.py
mypy_boto3_iot1click_projects-1.35.93.dist-info/LICENSE
mypy_boto3_iot1click_projects-1.35.93.dist-info/METADATA
mypy_boto3_iot1click_projects-1.35.93.dist-info/WHEEL
mypy_boto3_iot1click_projects-1.35.93.dist-info/top_level.txt
mypy_boto3_iot1click_projects-1.35.93.dist-info/RECORD
