Metadata-Version: 2.1
Name: mypy-boto3-iot1click-projects
Version: 1.35.93
Summary: Type annotations for boto3 IoT1ClickProjects 1.35.93 service generated with mypy-boto3-builder 8.8.0
Home-page: https://github.com/youtype/mypy_boto3_builder
Author: Vlad Emelianov
Author-email: vlad.emelianov.nz@gmail.com
License: MIT License
Project-URL: Documentation, https://youtype.github.io/boto3_stubs_docs/mypy_boto3_iot1click_projects/
Project-URL: Source, https://github.com/youtype/mypy_boto3_builder
Project-URL: Tracker, https://github.com/youtype/mypy_boto3_builder/issues
Keywords: boto3 iot1click-projects boto3-stubs type-annotations mypy typeshed autocomplete
Classifier: Development Status :: 5 - Production/Stable
Classifier: Intended Audience :: Developers
Classifier: Environment :: Console
Classifier: License :: OSI Approved :: MIT License
Classifier: Natural Language :: English
Classifier: Operating System :: OS Independent
Classifier: Programming Language :: Python :: 3
Classifier: Programming Language :: Python :: 3.8
Classifier: Programming Language :: Python :: 3.9
Classifier: Programming Language :: Python :: 3.10
Classifier: Programming Language :: Python :: 3.11
Classifier: Programming Language :: Python :: 3.12
Classifier: Programming Language :: Python :: 3.13
Classifier: Programming Language :: Python :: 3.14
Classifier: Programming Language :: Python :: 3 :: Only
Classifier: Programming Language :: Python :: Implementation :: CPython
Classifier: Typing :: Stubs Only
Requires-Python: >=3.8
License-File: LICENSE
Requires-Dist: typing-extensions; python_version < "3.12"
